<?xml version='1.0' encoding='utf-8'?><m:layout id='7884e73e-9abf-4fda-8612-941b323f1131' xmlns='http://www.w3.org/1999/xhtml' xmlns:m='http://schemas.mendix.com/forms/1.0'><m:arguments><m:argument><div data-mendix-id='36.Atlas_Core.Phone_Default.scrollContainer1' data-mendix-type='mxui.widget.VerticalScrollContainer' data-mendix-props='"fixed":true,"config":[{"position":"top"},{"position":"middle"},{"position":"bottom"}]' class='mx-scrollcontainer mx-scrollcontainer-vertical mx-scrollcontainer-fixed'><div class='mx-scrollcontainer-top '><div class='mx-scrollcontainer-wrapper'><div class='mx-header mx-name-header1'><div class='mx-header-center'><div data-mendix-id='36.2' data-mendix-type='mxui.widget.ReactWidgetWrapper' data-mendix-props='"widgetTree":[{"$widgetId":"36.2","widget":"Title","props":{"class":"","caption":{"$type":"ExpressionProperty","expression":{"expr":{"type":"variable","variable":"pageTitle"},"args":{}}}}}],"listenTargets":[]'></div></div><div class='mx-header-left'><div data-mx-placeholder='3bbe63fc-492b-4a34-9db8-939e9a95ad4b' class='mx-placeholder'></div></div><div class='mx-header-right'><div data-mx-placeholder='b95d4a25-0d65-4a51-a257-37774bd13143' class='mx-placeholder'></div></div></div></div></div><div class='mx-scrollcontainer-middle region-content'><div class='mx-scrollcontainer-wrapper'><div data-mx-placeholder='4e3e0182-d633-4c7a-83b8-8948c0c8a34a' class='mx-placeholder'></div></div></div><div class='mx-scrollcontainer-bottom region-bottombar'><div class='mx-scrollcontainer-wrapper'><div data-mendix-id='36.Atlas_Core.Phone_Default.simpleMenuBar1' data-mendix-type='mxui.widget.ReactWidgetWrapper' data-mendix-props='"widgetTree":[{"$widgetId":"36.Atlas_Core.Phone_Default.simpleMenuBar1","widget":"SimpleMenuBar","props":{"class":"mx-name-simpleMenuBar1 bottom-nav-text-icons","menu":[{"caption":{"$type":"TextProperty","value":"Home"},"icon":{"$type":"IconProperty","icon":{"type":"glyph","iconClass":"glyphicon-home"}},"action":null},{"caption":{"$type":"TextProperty","value":"Layouts"},"icon":{"$type":"IconProperty","icon":{"type":"glyph","iconClass":"glyphicon-book"}},"action":null},{"caption":{"$type":"TextProperty","value":"Templates"},"icon":{"$type":"IconProperty","icon":{"type":"glyph","iconClass":"glyphicon-file"}},"action":null},{"caption":{"$type":"TextProperty","value":"Widgets"},"icon":{"$type":"IconProperty","icon":{"type":"glyph","iconClass":"glyphicon-cog"}},"action":null}],"orientation":"horizontal"}}],"listenTargets":[]'></div></div></div></div></m:argument></m:arguments></m:layout>